Metadata-Version: 2.1
Name: pretrained-vit-pytorch
Version: 0.0.1
Summary: Visual Transformers (ViT) in PyTorch.
Home-page: https://github.com/lukemelas/ViT-PyTorch
Author: Luke
Author-email: luke.melas@gmail.com
License: Apache
Platform: UNKNOWN
Classifier: License :: OSI Approved :: Apache Software License
Classifier: Programming Language :: Python
Classifier: Programming Language :: Python :: 3
Classifier: Programming Language :: Python :: 3.6
Requires-Python: >=3.5.0
